setup.py
smsaero/__init__.py
smsaero.egg-info/PKG-INFO
smsaero.egg-info/SOURCES.txt
smsaero.egg-info/dependency_links.txt
smsaero.egg-info/not-zip-safe
smsaero.egg-info/requires.txt
smsaero.egg-info/top_level.txt