Metadata-Version: 1.0
Name: smsaero
Version: 1.1.0
Summary: send SMS via smsaero.ru
Home-page: https://github.com/sheregeda/smsaero
Author: Nikolay Sheregeda
Author-email: ns.sheregeda@gmail.com
License: MIT
Keywords: sms,sending
Platform: UNKNOWN
